socket_cli/__init__.py
socket_cli/logger.py
socket_cli/main.py
socket_cli/commands/__init__.py
socket_cli/commands/command.py
socket_cli/commands/command_options.py
socket_cli/completer/__init__.py
socket_cli/completer/completer.py
socket_cli/completer/socketio_completer.py
socket_cli/completer/unix_socket_completer.py
socket_cli/completer/websocket_completer.py
socket_cli/options/__init__.py
socket_cli/options/socketio_option.py
socket_cli/options/unix_socket_option.py
socket_cli/options/websocket_option.py
socket_cli/packages/__init__.py
socket_cli/packages/logger.py
socket_cli/packages/commands/__init__.py
socket_cli/packages/commands/command.py
socket_cli/packages/commands/command_options.py
socket_cli/packages/completer/__init__.py
socket_cli/packages/completer/completer.py
socket_cli/packages/completer/socketio_completer.py
socket_cli/packages/completer/unix_socket_completer.py
socket_cli/packages/completer/websocket_completer.py
socket_cli/packages/options/__init__.py
socket_cli/packages/options/socketio_option.py
socket_cli/packages/options/unix_socket_option.py
socket_cli/packages/options/websocket_option.py
socket_cli/packages/prompt/__init__.py
socket_cli/packages/prompt/factory.py
socket_cli/packages/prompt/prompt.py
socket_cli/packages/prompt/socketio_prompt.py
socket_cli/packages/prompt/unix_socket_prompt.py
socket_cli/packages/prompt/websocket_prompt.py
socket_cli/packages/runner/__init__.py
socket_cli/packages/runner/runner.py
socket_cli/packages/runner/socketio.py
socket_cli/packages/runner/unix_socket.py
socket_cli/packages/runner/websocket.py
socket_cli/packages/utils/__init__.py
socket_cli/packages/utils/find_matches.py
socket_cli/packages/utils/options_parser.py
socket_cli/packages/utils/token.py
socket_cli/prompt/__init__.py
socket_cli/prompt/prompt.py
socket_cli/prompt/socketio_prompt.py
socket_cli/prompt/unix_socket_prompt.py
socket_cli/prompt/websocket_prompt.py
socket_cli/runner/__init__.py
socket_cli/runner/runner.py
socket_cli-0.1.7.dist-info/METADATA
socket_cli-0.1.7.dist-info/WHEEL
socket_cli-0.1.7.dist-info/entry_points.txt
socket_cli-0.1.7.dist-info/top_level.txt
socket_cli-0.1.7.dist-info/RECORD
