Metadata-Version: 2.1
Name: socket-cli
Version: 0.1.7
Summary: CLI for SocketIO, WebSocket, Unix-Socket. With auto-completion and syntax highlighting.
Home-page: http://pypi.python.org/pypi/PackageName/
Author: gcaaa31928
Author-email: gcaaa31928@gmail.com
License: LICENSE.txt
Platform: UNKNOWN
Classifier: Intended Audience :: Developers
Classifier: Development Status :: 3 - Alpha
Classifier: Operating System :: Unix
Classifier: Topic :: Software Development
Classifier: Topic :: Software Development :: Libraries :: Python Modules
Classifier: License :: OSI Approved :: MIT License
Classifier: Programming Language :: Python :: 3
Classifier: Programming Language :: Python :: 3.4
Classifier: Programming Language :: Python :: 3.5
Classifier: Programming Language :: Python :: 3.6
Requires-Dist: click (>=4.0)
Requires-Dist: prompt-toolkit (>=2.0.10)
Requires-Dist: fuzzyfinder (>=2.1.0)
Requires-Dist: python-socketio (>=4.3.1)
Requires-Dist: pygments (>=2.4.2)
Requires-Dist: halo
Requires-Dist: websockets (>=8.1)
Requires-Dist: asyncio (>=3.4.3)
Requires-Dist: requests
